[
  {
    "links": {
      "patch": {
        "small": "https://images2.imgbox.com/3c/0e/T8iJcSN3_o.png",
        "large": "https://images2.imgbox.com/40/e3/GypSkayF_o.png"
      }
    },
    "rocket": "5e9d0d95eda69955f709d1eb",
    "success": false,
    "name": "FalconSat",
    "date_unix": 1143239400
  },
  {
    "links": {
      "patch": {
        "small": "https://images2.imgbox.com/4f/e3/I0lkuJ2e_o.png",
        "large": "https://images2.imgbox.com/be/e7/iNqsqVYM_o.png"
      }
    },
    "rocket": "5e9d0d95eda69955f709d1eb",
    "success": false,
    "date_unix": 1174439400
  }
]

